python_cosmograph/__init__.py
python_cosmograph/python_cosmograph.py
python_cosmograph-0.1.1.dist-info/METADATA
python_cosmograph-0.1.1.dist-info/WHEEL
python_cosmograph-0.1.1.dist-info/RECORD
