Metadata-Version: 2.1
Name: python-cosmograph
Version: 0.1.1
Summary: Cosmograph is a  library for scheduling asynchronous tasks using the `apscheduler` library. It provides decorators to easily schedule tasks at specific times, intervals, or dates.
Author: Iranildo Alves
Author-email: 117860354+IranTheCreator@users.noreply.github.com
Requires-Python: >=3.11,<4.0
Classifier: Programming Language :: Python :: 3
Classifier: Programming Language :: Python :: 3.11
Classifier: Programming Language :: Python :: 3.12
Requires-Dist: apscheduler (>=3.10.4,<4.0.0)
